Trimports/__init__.py
Trimports/arg_process.py
Trimports/cli.py
Trimports/trimport.py
Trimports/utils.py
trimports-0.1.2.dist-info/LICENSE.txt
trimports-0.1.2.dist-info/METADATA
trimports-0.1.2.dist-info/WHEEL
trimports-0.1.2.dist-info/entry_points.txt
trimports-0.1.2.dist-info/top_level.txt
trimports-0.1.2.dist-info/RECORD
