Metadata-Version: 2.1
Name: trimports
Version: 0.1.2
Summary: A python class which automatically removes unused imports from your Python script.
Home-page: https://github.com/amitjoshi9627/trimports
Author: Amit Joshi
Author-email: amitjoshi9627@gmail.com
License: MIT
Keywords: unused imports
Platform: UNKNOWN
Classifier: Development Status :: 5 - Production/Stable
Classifier: Intended Audience :: Developers
Classifier: License :: OSI Approved :: MIT License
Classifier: Programming Language :: Python :: 3
Classifier: Topic :: Software Development :: Libraries :: Python Modules
License-File: LICENSE.txt
